README.rst
setup.py
facets/__init__.py
facets/cache.py
facets/collections.py
facets/conf.py
facets/finders.py
facets/handlers.py
facets/models.py
facets/storages.py
facets/utils.py
facets/version.py
facets.egg-info/PKG-INFO
facets.egg-info/SOURCES.txt
facets.egg-info/dependency_links.txt
facets.egg-info/requires.txt
facets.egg-info/top_level.txt
facets/compilers/__init__.py
facets/compilers/base.py
facets/compilers/css.py
facets/compilers/js.py
facets/processors/__init__.py
facets/processors/base.py
facets/processors/css.py
facets/processors/gz.py
facets/processors/images.py
facets/processors/js.py
facets/templatetags/__init__.py
facets/templatetags/facets.py