Metadata-Version: 1.0
Name: facets
Version: 1.0.0
Summary: Asset manager for Django.
Home-page: https://github.com/olivier-m/django-facets
Author: Olivier Meunier
Author-email: olivier@neokraft.net
License: MIT License
Keywords: django assets css javascript compression
Platform: UNKNOWN
Classifier: Development Status :: 5 - Production/Stable
Classifier: Environment :: Web Environment
Classifier: Framework :: Django
Classifier: Intended Audience :: Developers
Classifier: License :: OSI Approved :: MIT License
Classifier: Operating System :: OS Independent
Classifier: Programming Language :: Python
Classifier: Topic :: Utilities
